makertools/__init__.py
makertools/mark_excel.py
makertools/mark_request.py
makertools/mark_sql.py
makertools/mark_sqlalchemy.py
makertools-1.1.1.dist-info/METADATA
makertools-1.1.1.dist-info/WHEEL
makertools-1.1.1.dist-info/top_level.txt
makertools-1.1.1.dist-info/RECORD
